midprint/__init__.py
midprint/hello.py
midprint-0.0.3.dist-info/METADATA
midprint-0.0.3.dist-info/WHEEL
midprint-0.0.3.dist-info/top_level.txt
midprint-0.0.3.dist-info/RECORD
